SeleniumLibrary/__init__.py
SeleniumLibrary/__init__.pyi
SeleniumLibrary/errors.py
SeleniumLibrary/base/__init__.py
SeleniumLibrary/base/context.py
SeleniumLibrary/base/librarycomponent.py
SeleniumLibrary/entry/__init__.py
SeleniumLibrary/entry/__main__.py
SeleniumLibrary/entry/get_versions.py
SeleniumLibrary/entry/translation.py
SeleniumLibrary/keywords/__init__.py
SeleniumLibrary/keywords/alert.py
SeleniumLibrary/keywords/browsermanagement.py
SeleniumLibrary/keywords/cookie.py
SeleniumLibrary/keywords/element.py
SeleniumLibrary/keywords/expectedconditions.py
SeleniumLibrary/keywords/formelement.py
SeleniumLibrary/keywords/frames.py
SeleniumLibrary/keywords/javascript.py
SeleniumLibrary/keywords/runonfailure.py
SeleniumLibrary/keywords/screenshot.py
SeleniumLibrary/keywords/selectelement.py
SeleniumLibrary/keywords/tableelement.py
SeleniumLibrary/keywords/waiting.py
SeleniumLibrary/keywords/window.py
SeleniumLibrary/keywords/webdrivertools/__init__.py
SeleniumLibrary/keywords/webdrivertools/sl_file_detector.py
SeleniumLibrary/keywords/webdrivertools/webdrivertools.py
SeleniumLibrary/locators/__init__.py
SeleniumLibrary/locators/customlocator.py
SeleniumLibrary/locators/elementfinder.py
SeleniumLibrary/locators/windowmanager.py
SeleniumLibrary/utils/__init__.py
SeleniumLibrary/utils/librarylistener.py
SeleniumLibrary/utils/path_formatter.py
SeleniumLibrary/utils/types.py
SeleniumLibrary/utils/events/__init__.py
SeleniumLibrary/utils/events/event.py
SeleniumLibrary/utils/events/scope_event.py
robotframework_seleniumlibrary-6.6.0.dist-info/LICENSE.txt
robotframework_seleniumlibrary-6.6.0.dist-info/METADATA
robotframework_seleniumlibrary-6.6.0.dist-info/WHEEL
robotframework_seleniumlibrary-6.6.0.dist-info/entry_points.txt
robotframework_seleniumlibrary-6.6.0.dist-info/top_level.txt
robotframework_seleniumlibrary-6.6.0.dist-info/RECORD
