Metadata-Version: 2.1
Name: robotframework-seleniumlibrary
Version: 6.6.0
Summary: Web testing library for Robot Framework
Home-page: https://github.com/robotframework/SeleniumLibrary
Author: Ed Manlove, Yuri Verweij, Lisa Crispin
Author-email: emanlove@verizon.net
License: Apache License 2.0
Keywords: robotframework testing testautomation selenium webdriver web
Platform: any
Classifier: Development Status :: 5 - Production/Stable
Classifier: License :: OSI Approved :: Apache Software License
Classifier: Operating System :: OS Independent
Classifier: Programming Language :: Python
Classifier: Programming Language :: Python :: 3
Classifier: Programming Language :: Python :: 3.8
Classifier: Programming Language :: Python :: 3.9
Classifier: Programming Language :: Python :: 3.10
Classifier: Programming Language :: Python :: 3.11
Classifier: Programming Language :: Python :: 3.12
Classifier: Programming Language :: Python :: 3 :: Only
Classifier: Topic :: Software Development :: Testing
Classifier: Framework :: Robot Framework
Classifier: Framework :: Robot Framework :: Library
Requires-Python: >=3.8, <=3.12
License-File: LICENSE.txt
Requires-Dist: selenium>=4.3.0
Requires-Dist: robotframework>=4.1.3
Requires-Dist: robotframework-pythonlibcore>=4.4.1
Requires-Dist: click>=8.1.7
